CHANGES.txt
LICENSE.txt
MANIFEST.in
README.txt
bootstrap.py
buildout.cfg
setup.cfg
setup.py
js/__init__.py
js.gridster.egg-info/PKG-INFO
js.gridster.egg-info/SOURCES.txt
js.gridster.egg-info/dependency_links.txt
js.gridster.egg-info/entry_points.txt
js.gridster.egg-info/namespace_packages.txt
js.gridster.egg-info/not-zip-safe
js.gridster.egg-info/requires.txt
js.gridster.egg-info/top_level.txt
js/gridster/__init__.py
js/gridster/test_gridster.txt
js/gridster/resources/README.txt
js/gridster/resources/jquery.collision.js
js/gridster/resources/jquery.collision.min.js
js/gridster/resources/jquery.coords.js
js/gridster/resources/jquery.coords.min.js
js/gridster/resources/jquery.draggable.js
js/gridster/resources/jquery.draggable.min.js
js/gridster/resources/jquery.gridster.css
js/gridster/resources/jquery.gridster.extras.js
js/gridster/resources/jquery.gridster.extras.min.js
js/gridster/resources/jquery.gridster.js
js/gridster/resources/jquery.gridster.min.css
js/gridster/resources/jquery.gridster.min.js
js/gridster/resources/utils.js
js/gridster/resources/utils.min.js
js/gridster/resources/dist/jquery.gridster.css
js/gridster/resources/dist/jquery.gridster.js
js/gridster/resources/dist/jquery.gridster.min.css
js/gridster/resources/dist/jquery.gridster.min.js
js/gridster/resources/dist/jquery.gridster.with-extras.js
js/gridster/resources/dist/jquery.gridster.with-extras.min.js