Metadata-Version: 1.0
Name: js.gridster
Version: 0.2.1
Summary: Fanstatic packaging of gridster
Home-page: https://github.com/j23d/js.gridster
Author: Marco Scheidhuber
Author-email: fanstatic@googlegroups.com
License: BSD
Keywords: fanstatic jquery gridster
Platform: UNKNOWN
